mlx_manager/__init__.py
mlx_manager/cli.py
mlx_manager/config.py
mlx_manager/database.py
mlx_manager/dependencies.py
mlx_manager/main.py
mlx_manager/menubar.py
mlx_manager/models.py
mlx_manager/types.py
mlx_manager/routers/__init__.py
mlx_manager/routers/auth.py
mlx_manager/routers/chat.py
mlx_manager/routers/mcp.py
mlx_manager/routers/models.py
mlx_manager/routers/profiles.py
mlx_manager/routers/servers.py
mlx_manager/routers/system.py
mlx_manager/services/__init__.py
mlx_manager/services/auth_service.py
mlx_manager/services/health_checker.py
mlx_manager/services/hf_api.py
mlx_manager/services/hf_client.py
mlx_manager/services/launchd.py
mlx_manager/services/manager_launchd.py
mlx_manager/services/parser_options.py
mlx_manager/services/server_manager.py
mlx_manager/static/apple-touch-icon-precomposed.png
mlx_manager/static/apple-touch-icon.png
mlx_manager/static/favicon-16x16.png
mlx_manager/static/favicon-32x32.png
mlx_manager/static/favicon.ico
mlx_manager/static/favicon.svg
mlx_manager/static/index.html
mlx_manager/static/_app/env.js
mlx_manager/static/_app/version.json
mlx_manager/static/_app/immutable/assets/app.BxKEnQiV.css
mlx_manager/static/_app/immutable/chunks/1cqaUJGZ.js
mlx_manager/static/_app/immutable/chunks/3fxp844U.js
mlx_manager/static/_app/immutable/chunks/B2MmRDq8.js
mlx_manager/static/_app/immutable/chunks/BCcEFCgH.js
mlx_manager/static/_app/immutable/chunks/BIZ-GM10.js
mlx_manager/static/_app/immutable/chunks/BQ-_QVTP.js
mlx_manager/static/_app/immutable/chunks/BWQjEkJe.js
mlx_manager/static/_app/immutable/chunks/BWpKPX3N.js
mlx_manager/static/_app/immutable/chunks/BmwZupMj.js
mlx_manager/static/_app/immutable/chunks/BrRL0KsS.js
mlx_manager/static/_app/immutable/chunks/C4CP8qua.js
mlx_manager/static/_app/immutable/chunks/CFz_a2k3.js
mlx_manager/static/_app/immutable/chunks/CLON3Y_x.js
mlx_manager/static/_app/immutable/chunks/CNYbWU2B.js
mlx_manager/static/_app/immutable/chunks/CbhfpbUc.js
mlx_manager/static/_app/immutable/chunks/CfIuuR-Z.js
mlx_manager-1.1.0.dist-info/METADATA
mlx_manager-1.1.0.dist-info/WHEEL
mlx_manager-1.1.0.dist-info/entry_points.txt
mlx_manager-1.1.0.dist-info/top_level.txt
mlx_manager-1.1.0.dist-info/RECORD
