Metadata-Version: 2.4
Name: mlx-manager
Version: 1.1.0
Summary: Web-based MLX model manager for Apple Silicon Macs
License: MIT
Project-URL: Homepage, https://github.com/tumma72/mlx-manager
Project-URL: Repository, https://github.com/tumma72/mlx-manager
Project-URL: Documentation, https://github.com/tumma72/mlx-manager#readme
Keywords: mlx,apple-silicon,llm,model-manager,fastapi
Classifier: Development Status :: 4 - Beta
Classifier: Environment :: MacOS X
Classifier: Framework :: FastAPI
Classifier: Intended Audience :: Developers
Classifier: License :: OSI Approved :: MIT License
Classifier: Operating System :: MacOS :: MacOS X
Classifier: Programming Language :: Python :: 3
Classifier: Programming Language :: Python :: 3.11
Classifier: Programming Language :: Python :: 3.12
Classifier: Topic :: Scientific/Engineering :: Artificial Intelligence
Requires-Python: <3.13,>=3.11
Requires-Dist: fastapi>=0.115.0
Requires-Dist: python-multipart>=0.0.6
Requires-Dist: uvicorn[standard]>=0.32.0
Requires-Dist: sqlmodel>=0.0.22
Requires-Dist: aiosqlite>=0.20.0
Requires-Dist: greenlet>=3.0.0
Requires-Dist: huggingface-hub>=0.27.0
Requires-Dist: psutil>=6.0.0
Requires-Dist: httpx>=0.28.0
Requires-Dist: pydantic-settings>=2.0.0
Requires-Dist: transformers>=5.0.0rc1
Requires-Dist: typer>=0.12.0
Requires-Dist: rapidfuzz>=3.0.0
Requires-Dist: rumps>=0.4.0; sys_platform == "darwin"
Requires-Dist: mlx-openai-server>=1.4.0; sys_platform == "darwin"
Requires-Dist: alembic>=1.18.1
Requires-Dist: pyjwt>=2.8.0
Requires-Dist: pwdlib[argon2]>=0.3.0
Requires-Dist: mlx-vlm>=0.3.9
Provides-Extra: dev
Requires-Dist: pytest>=8.0.0; extra == "dev"
Requires-Dist: pytest-asyncio>=0.24.0; extra == "dev"
Requires-Dist: pytest-cov>=4.0.0; extra == "dev"
Requires-Dist: ruff>=0.8.0; extra == "dev"
Requires-Dist: mypy>=1.13.0; extra == "dev"
Requires-Dist: build>=1.0.0; extra == "dev"
Requires-Dist: pre-commit>=3.5.0; extra == "dev"
Requires-Dist: types-psutil>=5.9.0; extra == "dev"
